wikipedia_multistream_extractor/__init__.py
wikipedia_multistream_extractor-0.0.2.dist-info/METADATA
wikipedia_multistream_extractor-0.0.2.dist-info/WHEEL
wikipedia_multistream_extractor-0.0.2.dist-info/entry_points.txt
wikipedia_multistream_extractor-0.0.2.dist-info/licenses/LICENSE
wikipedia_multistream_extractor-0.0.2.dist-info/RECORD
