Metadata-Version: 2.1
Name: wikipedia_multistream_extractor
Version: 0.0.2
Summary: This is a simple application that extracts articles from Wikipedia backup files.
Project-URL: Homepage, https://github.com/BillSchumacher/WikipediaMultistreamExtractort
Project-URL: Bug Tracker, https://github.com/BillSchumacher/WikipediaMultistreamExtractor/issues
Author-email: Bill Schumacher <34168009+BillSchumacher@users.noreply.github.com>
License-File: LICENSE
Classifier: License :: OSI Approved :: MIT License
Classifier: Operating System :: OS Independent
Classifier: Programming Language :: Python :: 3
Requires-Python: >=3.9
Requires-Dist: click
Requires-Dist: tqdm
